asteroids/max10/Simulation-DDS/Kadinsky.v

`default_nettype none

/* verilator lint_off WIDTH */

module Kadinsky(

  input  wire Sync_clk,           // Kommt von der DDS zurück

  // DDS

  output wire DDS_pw_dwn,

  output wire DDS_sclk,
  output wire DDS_cs,
  output wire DDS_io_update,
  output wire DDS_Reset,

  output wire [3:0] DDS_sdio,

  input wire [3:0] DDS_P

);



  // ######   Taktkonfiguration   #############################

  // Reset-Signal für die DDS mit dem Rohtakt generieren
  // Die schaltet nämlich den Takt aus, wenn sie unter Reset steht.

  reg [22:0] dds_reset_cnt = 0;
  wire dds_resetq = &dds_reset_cnt;
  always @(posedge Sync_clk) dds_reset_cnt <= dds_reset_cnt + !dds_resetq;

  assign DDS_pw_dwn = 0;
  assign DDS_Reset = ~dds_resetq;

  // Takt, der von der DDS zurück kommt für den Rest des Systems verwenden

  wire clk = Sync_clk; // 25 MHz (Start) oder 100 MHz (fertig initialisiert) von der DDS zurück

  // ######   Reset logic   #####################################

  wire reset_button = 1; // Dieses Board hat keinen Resetknopf.

  reg [7:0] reset_cnt = 0;
  wire resetq = &reset_cnt;

  always @(posedge clk) begin
    if (reset_button) reset_cnt <= reset_cnt + !resetq;
    else              reset_cnt <= 0;
  end

  // ######   DDS-Konfiguration   #############################

  // Beim ersten Anlauf erstmal die DDS konfigurieren.

  reg  [175:0] dds_shift_register = { // Die erste Füllung initialisiert die DDS, 6 Bytes werden rausgeschrieben, also 48 Bits.
  // 22*8-1:0                     //  FR1          PLL * 4      Default      Default
                                      8'b00000001, 8'b10010011, 8'b00000000, 8'b00000000,

                                  //  CSR          Ch 0 & 1
                                      8'b00000000, 8'b11000000,

                                  //  CFR          Default 0    Default 3    Default 2 + Matched Delays
                                      8'b00000011, 8'b00000000, 8'b00000011, 8'b00100000,

                                  //  CSR          4-Bit
                                      8'b00000000, 8'b00000110,

                                  //  Padding, wird nicht rausgeschoben
                                      80'h0
                                    };

  // Später die Frequenz- und Amplitudenregister aktualisieren. Dafür werden insgesamt 22 Bytes gebraucht.

                                 //  CSR          CH 0 / 1     Frequency    f 31-24      f 23-16      f 15-8       f 7-0        Amplitude                          ..    ........
  wire [175:0] dds_neuer_befehl   = {8'b00000000, 8'b01000110, 8'b00000100, ch0frequenz,                                        8'b00000110, 8'b00000000, 6'b000100, ch0amplitude,
                                     8'b00000000, 8'b10000110, 8'b00000100, ch1frequenz,                                        8'b00000110, 8'b00000000, 6'b000100, ch1amplitude};

  reg [8:0] dds_bit_counter = 0;
  reg four_bit_mode = 0;

  reg [7:0] zweites_update = 0;

  // Während des Resets und um den Bitbreiten-Wechsel herum /CS high setzen
  // IO-Update ist jeweils für zwei SCLK-Zyklen aktiv; die DDS reagiert aber nur auf die steigende Flanke.

  assign DDS_cs        =                                                                                ~resetq | (~four_bit_mode & (dds_bit_counter > (8 * 12 * 2)));
  assign DDS_io_update = (dds_bit_counter[8:1] == 0) | four_bit_mode & (dds_bit_counter[8:1] == zweites_update) | (~four_bit_mode & (dds_bit_counter[8:1] == 96+2));

  // Vordersten vier Bit aus dem Schieberegister an die DDS anlegen.

  assign DDS_sdio[3] = four_bit_mode ? dds_shift_register[175] : 1'b0;
  assign DDS_sdio[2] = four_bit_mode ? dds_shift_register[174] : 1'b0;
  assign DDS_sdio[1] = four_bit_mode ? dds_shift_register[173] : 1'b0;
  assign DDS_sdio[0] = four_bit_mode ? dds_shift_register[172] : dds_shift_register[175];

  assign DDS_sclk      = dds_bit_counter[0] & ~DDS_cs; // Die Taktleitung laufe mit 50 MHz während /CS low = aktiv ist.

  // Neufüllen des Schieberegisters, wenn das letzte Bit rausgeschoben worden ist.
  wire shift_reload = four_bit_mode ? dds_bit_counter == (2 * 22 * 2 - 1) : dds_bit_counter == (8 * 22 * 2 - 1) ;

  // Wenn der Schieberegister frisch geladen ist, soll die Grafikeinheit einen Weiterspringen.
  // So haben die Multiplizierer viel Zeit, die Pixeldaten zum Laden in die DDS zu skalieren.

  wire pixelschritt = dds_bit_counter == 0;

  always @(posedge clk)
  begin
    if (~resetq)
    begin
      // Während des Resets soll der Counter bei 0 bleiben. Damit ruht auch DDS_sclk.
      dds_bit_counter <= 0;
      // Noch ist die DDS frisch aus dem Reset im 1-Bit-Modus.
      four_bit_mode <= 0;
    end
    else
    begin
      // Bits hochzählen, und am Ende zurückspringen.
      dds_bit_counter <= shift_reload ? 0 : dds_bit_counter + 1 ;

      // DDS nimmt Daten auf der steigenden Flanke entgegen.
      // Wenn SCLK gerade High ist, also die negative Flanke bevorsteht, den Schieberegister weiterlaufen lassen.
      if (dds_bit_counter[0]) dds_shift_register <= shift_reload ? dds_neuer_befehl :
                                                   four_bit_mode ? {dds_shift_register[171:0], 4'b0000} :
                                                                   {dds_shift_register[174:0], 1'b0};

      // Nach dem ersten Neuladen ist die PLL im 4-Bit-Modus.
      if (shift_reload) four_bit_mode <= 1;
    end
  end

  // --------------------------------------------------------------------------
  //   Vektorgrafikeinheit
  // --------------------------------------------------------------------------

  wire  [9:0] ch0amplitude      = 10'd1023; // a << 1;
  wire  [9:0] ch1amplitude      = 10'd255; // a << 1;

  wire [31:0] ch0frequenz = 32'hABCD1234;
  wire [31:0] ch1frequenz = 32'hFEFE5A5A;

endmodule

asteroids/max10/Simulation-DDS/test_dds.v
`timescale 1ns/100ps  // 1 ns time unit, 100 ps resolution
`default_nettype none // Makes it easier to detect typos !

module test_dds;
    reg clk;
    always #5.0 clk = !clk;

    reg resetq = 0;


   Kadinsky _DDS(

   .Sync_clk(clk)

);

   /***************************************************************************/
   // Test sequence
   /***************************************************************************/

   integer i;
   initial begin
     $dumpfile("dds.vcd");    // create a VCD waveform dump
     $dumpvars(0, test_dds); // dump variable changes in the testbench
                              // and all modules under it

     clk = 0;
     resetq = 0;
     @(negedge clk);
     resetq = 1;

     for (i = 0; i < 1000; i = i + 1) begin
       @(negedge clk);
     end



     $finish();
   end
endmodule

asteroids/max10/Simulation-DDS/dds.vcd
$date
	Thu Apr 13 04:32:15 2023
$end
$version
	Icarus Verilog
$end
$timescale
	100ps
$end
$scope module test_dds $end
$var reg 1 ! clk $end
$var reg 1 " resetq $end
$var integer 32 # i [31:0] $end
$scope module _DDS $end
$var wire 4 $ DDS_P [3:0] $end
$var wire 1 % DDS_Reset $end
$var wire 1 & DDS_cs $end
$var wire 1 ' DDS_io_update $end
$var wire 1 ( DDS_pw_dwn $end
$var wire 1 ) DDS_sclk $end
$var wire 1 ! Sync_clk $end
$var wire 10 * ch0amplitude [9:0] $end
$var wire 32 + ch0frequenz [31:0] $end
$var wire 10 , ch1amplitude [9:0] $end
$var wire 32 - ch1frequenz [31:0] $end
$var wire 1 . clk $end
$var wire 176 / dds_neuer_befehl [175:0] $end
$var wire 1 0 reset_button $end
$var wire 1 1 shift_reload $end
$var wire 1 2 resetq $end
$var wire 1 3 pixelschritt $end
$var wire 1 4 dds_resetq $end
$var wire 4 5 DDS_sdio [3:0] $end
$var reg 9 6 dds_bit_counter [8:0] $end
$var reg 23 7 dds_reset_cnt [22:0] $end
$var reg 176 8 dds_shift_register [175:0] $end
$var reg 1 9 four_bit_mode $end
$var reg 8 : reset_cnt [7:0] $end
$var reg 8 ; zweites_update [7:0] $end
$upscope $end
$upscope $end
$enddefinitions $end
#0
$dumpvars
b0 ;
b0 :
09
b1100100110000000000000000000000001100000000000011000000000000001100100000000000000000011000000000000000000000000000000000000000000000000000000000000000000000000000000000 8
b0 7
b0 6
b0 5
04
13
02
01
10
b10001100000010010101011110011010001001000110100000001100000000000010011111111110000000010000110000001001111111011111110010110100101101000000110000000000001000011111111 /
0.
b11111110111111100101101001011010 -
b11111111 ,
b10101011110011010001001000110100 +
b1111111111 *
0)
0(
1'
1&
1%
bz $
bx #
0"
0!
$end
#50
b1 :
b1 7
1.
1!
#100
b0 #
1"
0.
0!
#150
b10 :
b10 7
1.
1!
#200
b1 #
0.
0!
#250
b11 :
b11 7
1.
1!
#300
b10 #
0.
0!
#350
b100 :
b100 7
1.
1!
#400
b11 #
0.
0!
#450
b101 :
b101 7
1.
1!
#500
b100 #
0.
0!
#550
b110 :
b110 7
1.
1!
#600
b101 #
0.
0!
#650
b111 :
b111 7
1.
1!
#700
b110 #
0.
0!
#750
b1000 :
b1000 7
1.
1!
#800
b111 #
0.
0!
#850
b1001 :
b1001 7
1.
1!
#900
b1000 #
0.
0!
#950
b1010 :
b1010 7
1.
1!
#1000
b1001 #
0.
0!
#1050
b1011 :
b1011 7
1.
1!
#1100
b1010 #
0.
0!
#1150
b1100 :
b1100 7
1.
1!
#1200
b1011 #
0.
0!
#1250
b1101 :
b1101 7
1.
1!
#1300
b1100 #
0.
0!
#1350
b1110 :
b1110 7
1.
1!
#1400
b1101 #
0.
0!
#1450
b1111 :
b1111 7
1.
1!
#1500
b1110 #
0.
0!
#1550
b10000 :
b10000 7
1.
1!
#1600
b1111 #
0.
0!
#1650
b10001 :
b10001 7
1.
1!
#1700
b10000 #
0.
0!
#1750
b10010 :
b10010 7
1.
1!
#1800
b10001 #
0.
0!
#1850
b10011 :
b10011 7
1.
1!
#1900
b10010 #
0.
0!
#1950
b10100 :
b10100 7
1.
1!
#2000
b10011 #
0.
0!
#2050
b10101 :
b10101 7
1.
1!
#2100
b10100 #
0.
0!
#2150
b10110 :
b10110 7
1.
1!
#2200
b10101 #
0.
0!
#2250
b10111 :
b10111 7
1.
1!
#2300
b10110 #
0.
0!
#2350
b11000 :
b11000 7
1.
1!
#2400
b10111 #
0.
0!
#2450
b11001 :
b11001 7
1.
1!
#2500
b11000 #
0.
0!
#2550
b11010 :
b11010 7
1.
1!
#2600
b11001 #
0.
0!
#2650
b11011 :
b11011 7
1.
1!
#2700
b11010 #
0.
0!
#2750
b11100 :
b11100 7
1.
1!
#2800
b11011 #
0.
0!
#2850
b11101 :
b11101 7
1.
1!
#2900
b11100 #
0.
0!
#2950
b11110 :
b11110 7
1.
1!
#3000
b11101 #
0.
0!
#3050
b11111 :
b11111 7
1.
1!
#3100
b11110 #
0.
0!
#3150
b100000 :
b100000 7
1.
1!
#3200
b11111 #
0.
0!
#3250
b100001 :
b100001 7
1.
1!
#3300
b100000 #
0.
0!
#3350
b100010 :
b100010 7
1.
1!
#3400
b100001 #
0.
0!
#3450
b100011 :
b100011 7
1.
1!
#3500
b100010 #
0.
0!
#3550
b100100 :
b100100 7
1.
1!
#3600
b100011 #
0.
0!
#3650
b100101 :
b100101 7
1.
1!
#3700
b100100 #
0.
0!
#3750
b100110 :
b100110 7
1.
1!
#3800
b100101 #
0.
0!
#3850
b100111 :
b100111 7
1.
1!
#3900
b100110 #
0.
0!
#3950
b101000 :
b101000 7
1.
1!
#4000
b100111 #
0.
0!
#4050
b101001 :
b101001 7
1.
1!
#4100
b101000 #
0.
0!
#4150
b101010 :
b101010 7
1.
1!
#4200
b101001 #
0.
0!
#4250
b101011 :
b101011 7
1.
1!
#4300
b101010 #
0.
0!
#4350
b101100 :
b101100 7
1.
1!
#4400
b101011 #
0.
0!
#4450
b101101 :
b101101 7
1.
1!
#4500
b101100 #
0.
0!
#4550
b101110 :
b101110 7
1.
1!
#4600
b101101 #
0.
0!
#4650
b101111 :
b101111 7
1.
1!
#4700
b101110 #
0.
0!
#4750
b110000 :
b110000 7
1.
1!
#4800
b101111 #
0.
0!
#4850
b110001 :
b110001 7
1.
1!
#4900
b110000 #
0.
0!
#4950
b110010 :
b110010 7
1.
1!
#5000
b110001 #
0.
0!
#5050
b110011 :
b110011 7
1.
1!
#5100
b110010 #
0.
0!
#5150
b110100 :
b110100 7
1.
1!
#5200
b110011 #
0.
0!
#5250
b110101 :
b110101 7
1.
1!
#5300
b110100 #
0.
0!
#5350
b110110 :
b110110 7
1.
1!
#5400
b110101 #
0.
0!
#5450
b110111 :
b110111 7
1.
1!
#5500
b110110 #
0.
0!
#5550
b111000 :
b111000 7
1.
1!
#5600
b110111 #
0.
0!
#5650
b111001 :
b111001 7
1.
1!
#5700
b111000 #
0.
0!
#5750
b111010 :
b111010 7
1.
1!
#5800
b111001 #
0.
0!
#5850
b111011 :
b111011 7
1.
1!
#5900
b111010 #
0.
0!
#5950
b111100 :
b111100 7
1.
1!
#6000
b111011 #
0.
0!
#6050
b111101 :
b111101 7
1.
1!
#6100
b111100 #
0.
0!
#6150
b111110 :
b111110 7
1.
1!
#6200
b111101 #
0.
0!
#6250
b111111 :
b111111 7
1.
1!
#6300
b111110 #
0.
0!
#6350
b1000000 :
b1000000 7
1.
1!
#6400
b111111 #
0.
0!
#6450
b1000001 :
b1000001 7
1.
1!
#6500
b1000000 #
0.
0!
#6550
b1000010 :
b1000010 7
1.
1!
#6600
b1000001 #
0.
0!
#6650
b1000011 :
b1000011 7
1.
1!
#6700
b1000010 #
0.
0!
#6750
b1000100 :
b1000100 7
1.
1!
#6800
b1000011 #
0.
0!
#6850
b1000101 :
b1000101 7
1.
1!
#6900
b1000100 #
0.
0!
#6950
b1000110 :
b1000110 7
1.
1!
#7000
b1000101 #
0.
0!
#7050
b1000111 :
b1000111 7
1.
1!
#7100
b1000110 #
0.
0!
#7150
b1001000 :
b1001000 7
1.
1!
#7200
b1000111 #
0.
0!
#7250
b1001001 :
b1001001 7
1.
1!
#7300
b1001000 #
0.
0!
#7350
b1001010 :
b1001010 7
1.
1!
#7400
b1001001 #
0.
0!
#7450
b1001011 :
b1001011 7
1.
1!
#7500
b1001010 #
0.
0!
#7550
b1001100 :
b1001100 7
1.
1!
#7600
b1001011 #
0.
0!
#7650
b1001101 :
b1001101 7
1.
1!
#7700
b1001100 #
0.
0!
#7750
b1001110 :
b1001110 7
1.
1!
#7800
b1001101 #
0.
0!
#7850
b1001111 :
b1001111 7
1.
1!
#7900
b1001110 #
0.
0!
#7950
b1010000 :
b1010000 7
1.
1!
#8000
b1001111 #
0.
0!
#8050
b1010001 :
b1010001 7
1.
1!
#8100
b1010000 #
0.
0!
#8150
b1010010 :
b1010010 7
1.
1!
#8200
b1010001 #
0.
0!
#8250
b1010011 :
b1010011 7
1.
1!
#8300
b1010010 #
0.
0!
#8350
b1010100 :
b1010100 7
1.
1!
#8400
b1010011 #
0.
0!
#8450
b1010101 :
b1010101 7
1.
1!
#8500
b1010100 #
0.
0!
#8550
b1010110 :
b1010110 7
1.
1!
#8600
b1010101 #
0.
0!
#8650
b1010111 :
b1010111 7
1.
1!
#8700
b1010110 #
0.
0!
#8750
b1011000 :
b1011000 7
1.
1!
#8800
b1010111 #
0.
0!
#8850
b1011001 :
b1011001 7
1.
1!
#8900
b1011000 #
0.
0!
#8950
b1011010 :
b1011010 7
1.
1!
#9000
b1011001 #
0.
0!
#9050
b1011011 :
b1011011 7
1.
1!
#9100
b1011010 #
0.
0!
#9150
b1011100 :
b1011100 7
1.
1!
#9200
b1011011 #
0.
0!
#9250
b1011101 :
b1011101 7
1.
1!
#9300
b1011100 #
0.
0!
#9350
b1011110 :
b1011110 7
1.
1!
#9400
b1011101 #
0.
0!
#9450
b1011111 :
b1011111 7
1.
1!
#9500
b1011110 #
0.
0!
#9550
b1100000 :
b1100000 7
1.
1!
#9600
b1011111 #
0.
0!
#9650
b1100001 :
b1100001 7
1.
1!
#9700
b1100000 #
0.
0!
#9750
b1100010 :
b1100010 7
1.
1!
#9800
b1100001 #
0.
0!
#9850
b1100011 :
b1100011 7
1.
1!
#9900
b1100010 #
0.
0!
#9950
b1100100 :
b1100100 7
1.
1!
#10000
b1100011 #
0.
0!
#10050
b1100101 :
b1100101 7
1.
1!
#10100
b1100100 #
0.
0!
#10150
b1100110 :
b1100110 7
1.
1!
#10200
b1100101 #
0.
0!
#10250
b1100111 :
b1100111 7
1.
1!
#10300
b1100110 #
0.
0!
#10350
b1101000 :
b1101000 7
1.
1!
#10400
b1100111 #
0.
0!
#10450
b1101001 :
b1101001 7
1.
1!
#10500
b1101000 #
0.
0!
#10550
b1101010 :
b1101010 7
1.
1!
#10600
b1101001 #
0.
0!
#10650
b1101011 :
b1101011 7
1.
1!
#10700
b1101010 #
0.
0!
#10750
b1101100 :
b1101100 7
1.
1!
#10800
b1101011 #
0.
0!
#10850
b1101101 :
b1101101 7
1.
1!
#10900
b1101100 #
0.
0!
#10950
b1101110 :
b1101110 7
1.
1!
#11000
b1101101 #
0.
0!
#11050
b1101111 :
b1101111 7
1.
1!
#11100
b1101110 #
0.
0!
#11150
b1110000 :
b1110000 7
1.
1!
#11200
b1101111 #
0.
0!
#11250
b1110001 :
b1110001 7
1.
1!
#11300
b1110000 #
0.
0!
#11350
b1110010 :
b1110010 7
1.
1!
#11400
b1110001 #
0.
0!
#11450
b1110011 :
b1110011 7
1.
1!
#11500
b1110010 #
0.
0!
#11550
b1110100 :
b1110100 7
1.
1!
#11600
b1110011 #
0.
0!
#11650
b1110101 :
b1110101 7
1.
1!
#11700
b1110100 #
0.
0!
#11750
b1110110 :
b1110110 7
1.
1!
#11800
b1110101 #
0.
0!
#11850
b1110111 :
b1110111 7
1.
1!
#11900
b1110110 #
0.
0!
#11950
b1111000 :
b1111000 7
1.
1!
#12000
b1110111 #
0.
0!
#12050
b1111001 :
b1111001 7
1.
1!
#12100
b1111000 #
0.
0!
#12150
b1111010 :
b1111010 7
1.
1!
#12200
b1111001 #
0.
0!
#12250
b1111011 :
b1111011 7
1.
1!
#12300
b1111010 #
0.
0!
#12350
b1111100 :
b1111100 7
1.
1!
#12400
b1111011 #
0.
0!
#12450
b1111101 :
b1111101 7
1.
1!
#12500
b1111100 #
0.
0!
#12550
b1111110 :
b1111110 7
1.
1!
#12600
b1111101 #
0.
0!
#12650
b1111111 :
b1111111 7
1.
1!
#12700
b1111110 #
0.
0!
#12750
b10000000 :
b10000000 7
1.
1!
#12800
b1111111 #
0.
0!
#12850
b10000001 :
b10000001 7
1.
1!
#12900
b10000000 #
0.
0!
#12950
b10000010 :
b10000010 7
1.
1!
#13000
b10000001 #
0.
0!
#13050
b10000011 :
b10000011 7
1.
1!
#13100
b10000010 #
0.
0!
#13150
b10000100 :
b10000100 7
1.
1!
#13200
b10000011 #
0.
0!
#13250
b10000101 :
b10000101 7
1.
1!
#13300
b10000100 #
0.
0!
#13350
b10000110 :
b10000110 7
1.
1!
#13400
b10000101 #
0.
0!
#13450
b10000111 :
b10000111 7
1.
1!
#13500
b10000110 #
0.
0!
#13550
b10001000 :
b10001000 7
1.
1!
#13600
b10000111 #
0.
0!
#13650
b10001001 :
b10001001 7
1.
1!
#13700
b10001000 #
0.
0!
#13750
b10001010 :
b10001010 7
1.
1!
#13800
b10001001 #
0.
0!
#13850
b10001011 :
b10001011 7
1.
1!
#13900
b10001010 #
0.
0!
#13950
b10001100 :
b10001100 7
1.
1!
#14000
b10001011 #
0.
0!
#14050
b10001101 :
b10001101 7
1.
1!
#14100
b10001100 #
0.
0!
#14150
b10001110 :
b10001110 7
1.
1!
#14200
b10001101 #
0.
0!
#14250
b10001111 :
b10001111 7
1.
1!
#14300
b10001110 #
0.
0!
#14350
b10010000 :
b10010000 7
1.
1!
#14400
b10001111 #
0.
0!
#14450
b10010001 :
b10010001 7
1.
1!
#14500
b10010000 #
0.
0!
#14550
b10010010 :
b10010010 7
1.
1!
#14600
b10010001 #
0.
0!
#14650
b10010011 :
b10010011 7
1.
1!
#14700
b10010010 #
0.
0!
#14750
b10010100 :
b10010100 7
1.
1!
#14800
b10010011 #
0.
0!
#14850
b10010101 :
b10010101 7
1.
1!
#14900
b10010100 #
0.
0!
#14950
b10010110 :
b10010110 7
1.
1!
#15000
b10010101 #
0.
0!
#15050
b10010111 :
b10010111 7
1.
1!
#15100
b10010110 #
0.
0!
#15150
b10011000 :
b10011000 7
1.
1!
#15200
b10010111 #
0.
0!
#15250
b10011001 :
b10011001 7
1.
1!
#15300
b10011000 #
0.
0!
#15350
b10011010 :
b10011010 7
1.
1!
#15400
b10011001 #
0.
0!
#15450
b10011011 :
b10011011 7
1.
1!
#15500
b10011010 #
0.
0!
#15550
b10011100 :
b10011100 7
1.
1!
#15600
b10011011 #
0.
0!
#15650
b10011101 :
b10011101 7
1.
1!
#15700
b10011100 #
0.
0!
#15750
b10011110 :
b10011110 7
1.
1!
#15800
b10011101 #
0.
0!
#15850
b10011111 :
b10011111 7
1.
1!
#15900
b10011110 #
0.
0!
#15950
b10100000 :
b10100000 7
1.
1!
#16000
b10011111 #
0.
0!
#16050
b10100001 :
b10100001 7
1.
1!
#16100
b10100000 #
0.
0!
#16150
b10100010 :
b10100010 7
1.
1!
#16200
b10100001 #
0.
0!
#16250
b10100011 :
b10100011 7
1.
1!
#16300
b10100010 #
0.
0!
#16350
b10100100 :
b10100100 7
1.
1!
#16400
b10100011 #
0.
0!
#16450
b10100101 :
b10100101 7
1.
1!
#16500
b10100100 #
0.
0!
#16550
b10100110 :
b10100110 7
1.
1!
#16600
b10100101 #
0.
0!
#16650
b10100111 :
b10100111 7
1.
1!
#16700
b10100110 #
0.
0!
#16750
b10101000 :
b10101000 7
1.
1!
#16800
b10100111 #
0.
0!
#16850
b10101001 :
b10101001 7
1.
1!
#16900
b10101000 #
0.
0!
#16950
b10101010 :
b10101010 7
1.
1!
#17000
b10101001 #
0.
0!
#17050
b10101011 :
b10101011 7
1.
1!
#17100
b10101010 #
0.
0!
#17150
b10101100 :
b10101100 7
1.
1!
#17200
b10101011 #
0.
0!
#17250
b10101101 :
b10101101 7
1.
1!
#17300
b10101100 #
0.
0!
#17350
b10101110 :
b10101110 7
1.
1!
#17400
b10101101 #
0.
0!
#17450
b10101111 :
b10101111 7
1.
1!
#17500
b10101110 #
0.
0!
#17550
b10110000 :
b10110000 7
1.
1!
#17600
b10101111 #
0.
0!
#17650
b10110001 :
b10110001 7
1.
1!
#17700
b10110000 #
0.
0!
#17750
b10110010 :
b10110010 7
1.
1!
#17800
b10110001 #
0.
0!
#17850
b10110011 :
b10110011 7
1.
1!
#17900
b10110010 #
0.
0!
#17950
b10110100 :
b10110100 7
1.
1!
#18000
b10110011 #
0.
0!
#18050
b10110101 :
b10110101 7
1.
1!
#18100
b10110100 #
0.
0!
#18150
b10110110 :
b10110110 7
1.
1!
#18200
b10110101 #
0.
0!
#18250
b10110111 :
b10110111 7
1.
1!
#18300
b10110110 #
0.
0!
#18350
b10111000 :
b10111000 7
1.
1!
#18400
b10110111 #
0.
0!
#18450
b10111001 :
b10111001 7
1.
1!
#18500
b10111000 #
0.
0!
#18550
b10111010 :
b10111010 7
1.
1!
#18600
b10111001 #
0.
0!
#18650
b10111011 :
b10111011 7
1.
1!
#18700
b10111010 #
0.
0!
#18750
b10111100 :
b10111100 7
1.
1!
#18800
b10111011 #
0.
0!
#18850
b10111101 :
b10111101 7
1.
1!
#18900
b10111100 #
0.
0!
#18950
b10111110 :
b10111110 7
1.
1!
#19000
b10111101 #
0.
0!
#19050
b10111111 :
b10111111 7
1.
1!
#19100
b10111110 #
0.
0!
#19150
b11000000 :
b11000000 7
1.
1!
#19200
b10111111 #
0.
0!
#19250
b11000001 :
b11000001 7
1.
1!
#19300
b11000000 #
0.
0!
#19350
b11000010 :
b11000010 7
1.
1!
#19400
b11000001 #
0.
0!
#19450
b11000011 :
b11000011 7
1.
1!
#19500
b11000010 #
0.
0!
#19550
b11000100 :
b11000100 7
1.
1!
#19600
b11000011 #
0.
0!
#19650
b11000101 :
b11000101 7
1.
1!
#19700
b11000100 #
0.
0!
#19750
b11000110 :
b11000110 7
1.
1!
#19800
b11000101 #
0.
0!
#19850
b11000111 :
b11000111 7
1.
1!
#19900
b11000110 #
0.
0!
#19950
b11001000 :
b11001000 7
1.
1!
#20000
b11000111 #
0.
0!
#20050
b11001001 :
b11001001 7
1.
1!
#20100
b11001000 #
0.
0!
#20150
b11001010 :
b11001010 7
1.
1!
#20200
b11001001 #
0.
0!
#20250
b11001011 :
b11001011 7
1.
1!
#20300
b11001010 #
0.
0!
#20350
b11001100 :
b11001100 7
1.
1!
#20400
b11001011 #
0.
0!
#20450
b11001101 :
b11001101 7
1.
1!
#20500
b11001100 #
0.
0!
#20550
b11001110 :
b11001110 7
1.
1!
#20600
b11001101 #
0.
0!
#20650
b11001111 :
b11001111 7
1.
1!
#20700
b11001110 #
0.
0!
#20750
b11010000 :
b11010000 7
1.
1!
#20800
b11001111 #
0.
0!
#20850
b11010001 :
b11010001 7
1.
1!
#20900
b11010000 #
0.
0!
#20950
b11010010 :
b11010010 7
1.
1!
#21000
b11010001 #
0.
0!
#21050
b11010011 :
b11010011 7
1.
1!
#21100
b11010010 #
0.
0!
#21150
b11010100 :
b11010100 7
1.
1!
#21200
b11010011 #
0.
0!
#21250
b11010101 :
b11010101 7
1.
1!
#21300
b11010100 #
0.
0!
#21350
b11010110 :
b11010110 7
1.
1!
#21400
b11010101 #
0.
0!
#21450
b11010111 :
b11010111 7
1.
1!
#21500
b11010110 #
0.
0!
#21550
b11011000 :
b11011000 7
1.
1!
#21600
b11010111 #
0.
0!
#21650
b11011001 :
b11011001 7
1.
1!
#21700
b11011000 #
0.
0!
#21750
b11011010 :
b11011010 7
1.
1!
#21800
b11011001 #
0.
0!
#21850
b11011011 :
b11011011 7
1.
1!
#21900
b11011010 #
0.
0!
#21950
b11011100 :
b11011100 7
1.
1!
#22000
b11011011 #
0.
0!
#22050
b11011101 :
b11011101 7
1.
1!
#22100
b11011100 #
0.
0!
#22150
b11011110 :
b11011110 7
1.
1!
#22200
b11011101 #
0.
0!
#22250
b11011111 :
b11011111 7
1.
1!
#22300
b11011110 #
0.
0!
#22350
b11100000 :
b11100000 7
1.
1!
#22400
b11011111 #
0.
0!
#22450
b11100001 :
b11100001 7
1.
1!
#22500
b11100000 #
0.
0!
#22550
b11100010 :
b11100010 7
1.
1!
#22600
b11100001 #
0.
0!
#22650
b11100011 :
b11100011 7
1.
1!
#22700
b11100010 #
0.
0!
#22750
b11100100 :
b11100100 7
1.
1!
#22800
b11100011 #
0.
0!
#22850
b11100101 :
b11100101 7
1.
1!
#22900
b11100100 #
0.
0!
#22950
b11100110 :
b11100110 7
1.
1!
#23000
b11100101 #
0.
0!
#23050
b11100111 :
b11100111 7
1.
1!
#23100
b11100110 #
0.
0!
#23150
b11101000 :
b11101000 7
1.
1!
#23200
b11100111 #
0.
0!
#23250
b11101001 :
b11101001 7
1.
1!
#23300
b11101000 #
0.
0!
#23350
b11101010 :
b11101010 7
1.
1!
#23400
b11101001 #
0.
0!
#23450
b11101011 :
b11101011 7
1.
1!
#23500
b11101010 #
0.
0!
#23550
b11101100 :
b11101100 7
1.
1!
#23600
b11101011 #
0.
0!
#23650
b11101101 :
b11101101 7
1.
1!
#23700
b11101100 #
0.
0!
#23750
b11101110 :
b11101110 7
1.
1!
#23800
b11101101 #
0.
0!
#23850
b11101111 :
b11101111 7
1.
1!
#23900
b11101110 #
0.
0!
#23950
b11110000 :
b11110000 7
1.
1!
#24000
b11101111 #
0.
0!
#24050
b11110001 :
b11110001 7
1.
1!
#24100
b11110000 #
0.
0!
#24150
b11110010 :
b11110010 7
1.
1!
#24200
b11110001 #
0.
0!
#24250
b11110011 :
b11110011 7
1.
1!
#24300
b11110010 #
0.
0!
#24350
b11110100 :
b11110100 7
1.
1!
#24400
b11110011 #
0.
0!
#24450
b11110101 :
b11110101 7
1.
1!
#24500
b11110100 #
0.
0!
#24550
b11110110 :
b11110110 7
1.
1!
#24600
b11110101 #
0.
0!
#24650
b11110111 :
b11110111 7
1.
1!
#24700
b11110110 #
0.
0!
#24750
b11111000 :
b11111000 7
1.
1!
#24800
b11110111 #
0.
0!
#24850
b11111001 :
b11111001 7
1.
1!
#24900
b11111000 #
0.
0!
#24950
b11111010 :
b11111010 7
1.
1!
#25000
b11111001 #
0.
0!
#25050
b11111011 :
b11111011 7
1.
1!
#25100
b11111010 #
0.
0!
#25150
b11111100 :
b11111100 7
1.
1!
#25200
b11111011 #
0.
0!
#25250
b11111101 :
b11111101 7
1.
1!
#25300
b11111100 #
0.
0!
#25350
b11111110 :
b11111110 7
1.
1!
#25400
b11111101 #
0.
0!
#25450
0&
12
b11111111 :
b11111111 7
1.
1!
#25500
b11111110 #
0.
0!
#25550
1)
03
b1 6
b100000000 7
1.
1!
#25600
b11111111 #
0.
0!
#25650
0'
0)
b11001001100000000000000000000000011000000000000110000000000000011001000000000000000000110000000000000000000000000000000000000000000000000000000000000000000000000000000000 8
b10 6
b100000001 7
1.
1!
#25700
b100000000 #
0.
0!
#25750
1)
b11 6
b100000010 7
1.
1!
#25800
b100000001 #
0.
0!
#25850
0)
b110010011000000000000000000000000110000000000001100000000000000110010000000000000000001100000000000000000000000000000000000000000000000000000000000000000000000000000000000 8
b100 6
b100000011 7
1.
1!
#25900
b100000010 #
0.
0!
#25950
1)
b101 6
b100000100 7
1.
1!
#26000
b100000011 #
0.
0!
#26050
0)
b1100100110000000000000000000000001100000000000011000000000000001100100000000000000000011000000000000000000000000000000000000000000000000000000000000000000000000000000000000 8
b110 6
b100000101 7
1.
1!
#26100
b100000100 #
0.
0!
#26150
1)
b111 6
b100000110 7
1.
1!
#26200
b100000101 #
0.
0!
#26250
0)
b11001001100000000000000000000000011000000000000110000000000000011001000000000000000000110000000000000000000000000000000000000000000000000000000000000000000000000000000000000 8
b1000 6
b100000111 7
1.
1!
#26300
b100000110 #
0.
0!
#26350
1)
b1001 6
b100001000 7
1.
1!
#26400
b100000111 #
0.
0!
#26450
0)
b110010011000000000000000000000000110000000000001100000000000000110010000000000000000001100000000000000000000000000000000000000000000000000000000000000000000000000000000000000 8
b1010 6
b100001001 7
1.
1!
#26500
b100001000 #
0.
0!
#26550
1)
b1011 6
b100001010 7
1.
1!
#26600
b100001001 #
0.
0!
